// 
// Decompiled by Procyon v0.6-prerelease
// 

package com.formdev.flatlaf.util;

class LoggingFacadeImpl implements LoggingFacade
{
    private static final System.Logger LOG;
    
    LoggingFacadeImpl() {
        // 
        // This method could not be decompiled.
        // 
        // Original Bytecode:
        // 
        //     2: invokevirtual   java/lang/System$Logger$Level.ERROR:()Ljava/lang/System$Logger$Level;
        // 
        // The error that occurred was:
        // 
        // java.lang.NullPointerException
        //     at com.strobel.decompiler.ast.AstBuilder.performStackAnalysis(AstBuilder.java:2220)
        //     at com.strobel.decompiler.ast.AstBuilder.build(AstBuilder.java:108)
        //     at com.strobel.decompiler.languages.java.ast.AstMethodBodyBuilder.createMethodBody(AstMethodBodyBuilder.java:206)
        //     at com.strobel.decompiler.languages.java.ast.AstMethodBodyBuilder.createMethodBody(AstMethodBodyBuilder.java:94)
        //     at com.strobel.decompiler.languages.java.ast.AstBuilder.createMethodBody(AstBuilder.java:840)
        //     at com.strobel.decompiler.languages.java.ast.AstBuilder.createConstructor(AstBuilder.java:771)
        //     at com.strobel.decompiler.languages.java.ast.AstBuilder.addTypeMembers(AstBuilder.java:607)
        //     at com.strobel.decompiler.languages.java.ast.AstBuilder.createTypeCore(AstBuilder.java:577)
        //     at com.strobel.decompiler.languages.java.ast.AstBuilder.createTypeNoCache(AstBuilder.java:193)
        //     at com.strobel.decompiler.languages.java.ast.AstBuilder.createType(AstBuilder.java:160)
        //     at com.strobel.decompiler.languages.java.ast.AstBuilder.addType(AstBuilder.java:135)
        //     at com.strobel.decompiler.languages.java.JavaLanguage.buildAst(JavaLanguage.java:71)
        //     at com.strobel.decompiler.languages.java.JavaLanguage.decompileType(JavaLanguage.java:59)
        //     at com.strobel.decompiler.DecompilerDriver.decompileType(DecompilerDriver.java:333)
        //     at com.strobel.decompiler.DecompilerDriver.decompileJar(DecompilerDriver.java:254)
        //     at com.strobel.decompiler.DecompilerDriver.main(DecompilerDriver.java:144)
        // 
        throw new IllegalStateException("An error occurred while decompiling this method.");
    }
    
    @Override
    public void logSevere(final String message, final Throwable t) {
        // 
        // This method could not be decompiled.
        // 
        // Original Bytecode:
        // 
        //     1: nop            
        //     2: fload_0         /* this */
        //     3: nop            
        //     4: aconst_null    
        //     5: nop            
        //     6: fload_2         /* t */
        //     7: nop            
        //     8: sipush          1
        //    11: nop            
        //    12: saload         
        //    13: nop            
        // 
        // The error that occurred was:
        // 
        // java.lang.NullPointerException
        //     at com.strobel.decompiler.ast.AstBuilder.performStackAnalysis(AstBuilder.java:2220)
        //     at com.strobel.decompiler.ast.AstBuilder.build(AstBuilder.java:108)
        //     at com.strobel.decompiler.languages.java.ast.AstMethodBodyBuilder.createMethodBody(AstMethodBodyBuilder.java:206)
        //     at com.strobel.decompiler.languages.java.ast.AstMethodBodyBuilder.createMethodBody(AstMethodBodyBuilder.java:94)
        //     at com.strobel.decompiler.languages.java.ast.AstBuilder.createMethodBody(AstBuilder.java:840)
        //     at com.strobel.decompiler.languages.java.ast.AstBuilder.createMethod(AstBuilder.java:733)
        //     at com.strobel.decompiler.languages.java.ast.AstBuilder.addTypeMembers(AstBuilder.java:610)
        //     at com.strobel.decompiler.languages.java.ast.AstBuilder.createTypeCore(AstBuilder.java:577)
        //     at com.strobel.decompiler.languages.java.ast.AstBuilder.createTypeNoCache(AstBuilder.java:193)
        //     at com.strobel.decompiler.languages.java.ast.AstBuilder.createType(AstBuilder.java:160)
        //     at com.strobel.decompiler.languages.java.ast.AstBuilder.addType(AstBuilder.java:135)
        //     at com.strobel.decompiler.languages.java.JavaLanguage.buildAst(JavaLanguage.java:71)
        //     at com.strobel.decompiler.languages.java.JavaLanguage.decompileType(JavaLanguage.java:59)
        //     at com.strobel.decompiler.DecompilerDriver.decompileType(DecompilerDriver.java:333)
        //     at com.strobel.decompiler.DecompilerDriver.decompileJar(DecompilerDriver.java:254)
        //     at com.strobel.decompiler.DecompilerDriver.main(DecompilerDriver.java:144)
        // 
        throw new IllegalStateException("An error occurred while decompiling this method.");
    }
    
    @Override
    public void logConfig(final String message, final Throwable t) {
        // 
        // This method could not be decompiled.
        // 
        // Original Bytecode:
        // 
        //     1: nop            
        //     2: iconst_5       
        //     3: nop            
        //     4: dload_2         /* t */
        //     5: nop            
        //     6: fconst_0       
        //     7: nop            
        //     8: aconst_null    
        //     9: nop            
        //    10: saload         
        //    11: nop            
        //    12: nop            
        //    13: nop            
        // 
        // The error that occurred was:
        // 
        // java.lang.ArrayIndexOutOfBoundsException: -1
        //     at java.util.ArrayList.elementData(Unknown Source)
        //     at java.util.ArrayList.get(Unknown Source)
        //     at com.strobel.assembler.ir.StackMappingVisitor.getStackValue(StackMappingVisitor.java:68)
        //     at com.strobel.decompiler.ast.AstBuilder.createModifiedStack(AstBuilder.java:2636)
        //     at com.strobel.decompiler.ast.AstBuilder.performStackAnalysis(AstBuilder.java:2090)
        //     at com.strobel.decompiler.ast.AstBuilder.build(AstBuilder.java:108)
        //     at com.strobel.decompiler.languages.java.ast.AstMethodBodyBuilder.createMethodBody(AstMethodBodyBuilder.java:206)
        //     at com.strobel.decompiler.languages.java.ast.AstMethodBodyBuilder.createMethodBody(AstMethodBodyBuilder.java:94)
        //     at com.strobel.decompiler.languages.java.ast.AstBuilder.createMethodBody(AstBuilder.java:840)
        //     at com.strobel.decompiler.languages.java.ast.AstBuilder.createMethod(AstBuilder.java:733)
        //     at com.strobel.decompiler.languages.java.ast.AstBuilder.addTypeMembers(AstBuilder.java:610)
        //     at com.strobel.decompiler.languages.java.ast.AstBuilder.createTypeCore(AstBuilder.java:577)
        //     at com.strobel.decompiler.languages.java.ast.AstBuilder.createTypeNoCache(AstBuilder.java:193)
        //     at com.strobel.decompiler.languages.java.ast.AstBuilder.createType(AstBuilder.java:160)
        //     at com.strobel.decompiler.languages.java.ast.AstBuilder.addType(AstBuilder.java:135)
        //     at com.strobel.decompiler.languages.java.JavaLanguage.buildAst(JavaLanguage.java:71)
        //     at com.strobel.decompiler.languages.java.JavaLanguage.decompileType(JavaLanguage.java:59)
        //     at com.strobel.decompiler.DecompilerDriver.decompileType(DecompilerDriver.java:333)
        //     at com.strobel.decompiler.DecompilerDriver.decompileJar(DecompilerDriver.java:254)
        //     at com.strobel.decompiler.DecompilerDriver.main(DecompilerDriver.java:144)
        // 
        throw new IllegalStateException("An error occurred while decompiling this method.");
    }
    
    static {
        // 
        // This method could not be decompiled.
        // 
        // Could not show original bytecode, likely due to the same error.
        // 
        // The error that occurred was:
        // 
        // java.lang.ArrayIndexOutOfBoundsException
        //     at com.strobel.assembler.ir.attributes.CodeAttribute.<init>(CodeAttribute.java:60)
        //     at com.strobel.assembler.metadata.MethodDefinition.tryLoadBody(MethodDefinition.java:700)
        //     at com.strobel.assembler.metadata.MethodDefinition.getBody(MethodDefinition.java:83)
        //     at com.strobel.decompiler.languages.java.ast.AstMethodBodyBuilder.createMethodBody(AstMethodBodyBuilder.java:197)
        //     at com.strobel.decompiler.languages.java.ast.AstMethodBodyBuilder.createMethodBody(AstMethodBodyBuilder.java:94)
        //     at com.strobel.decompiler.languages.java.ast.AstBuilder.createMethodBody(AstBuilder.java:840)
        //     at com.strobel.decompiler.languages.java.ast.AstBuilder.createMethod(AstBuilder.java:733)
        //     at com.strobel.decompiler.languages.java.ast.AstBuilder.addTypeMembers(AstBuilder.java:610)
        //     at com.strobel.decompiler.languages.java.ast.AstBuilder.createTypeCore(AstBuilder.java:577)
        //     at com.strobel.decompiler.languages.java.ast.AstBuilder.createTypeNoCache(AstBuilder.java:193)
        //     at com.strobel.decompiler.languages.java.ast.AstBuilder.createType(AstBuilder.java:160)
        //     at com.strobel.decompiler.languages.java.ast.AstBuilder.addType(AstBuilder.java:135)
        //     at com.strobel.decompiler.languages.java.JavaLanguage.buildAst(JavaLanguage.java:71)
        //     at com.strobel.decompiler.languages.java.JavaLanguage.decompileType(JavaLanguage.java:59)
        //     at com.strobel.decompiler.DecompilerDriver.decompileType(DecompilerDriver.java:333)
        //     at com.strobel.decompiler.DecompilerDriver.decompileJar(DecompilerDriver.java:254)
        //     at com.strobel.decompiler.DecompilerDriver.main(DecompilerDriver.java:144)
        // 
        throw new IllegalStateException("An error occurred while decompiling this method.");
    }
}
